[
    {
        "imageSrc": "/img/clients/client-1.png",
        "altText": "Client 1"
    },
    {
        "imageSrc": "/img/clients/client-2.png",
        "altText": "Client 2"
    },
    {
        "imageSrc": "/img/clients/client-3.png",
        "altText": "Client 3"
    },
    {
        "imageSrc": "/img/clients/client-4.png",
        "altText": "Client 4"
    },
    {
        "imageSrc": "/img/clients/client-5.png",
        "altText": "Client 5"
    },
    {
        "imageSrc": "/img/clients/client-6.png",
        "altText": "Client 6"
    },
    {
        "imageSrc": "/img/clients/client-7.png",
        "altText": "Client 7"
    },
    {
        "imageSrc": "/img/clients/client-8.png",
        "altText": "Client 8"
    }
]